LICENSE
README.md
setup.py
src/leap/LEAP.py
src/leap/__init__.py
src/leap/fastformerLM/__init__.py
src/leap/fastformerLM/fastformer.py
src/leap/fastformerLM/strip.py
src/leap_transformer.egg-info/PKG-INFO
src/leap_transformer.egg-info/SOURCES.txt
src/leap_transformer.egg-info/dependency_links.txt
src/leap_transformer.egg-info/requires.txt
src/leap_transformer.egg-info/top_level.txt