Metadata-Version: 2.1
Name: leap-transformer
Version: 0.1.1
Summary: Linear Explainable Attention in Parallel (LEAP) for causal language modeling (also implements fastformer)
Home-page: https://github.com/mtanghu/Additive-Attention-Is-Not-All-You-Need-Maybe
Author: Michael Hu
Author-email: prmhu@yahoo.com
License: CC0 1.0 Universal
Keywords: linear transformer NLP deep learning pytorch
License-File: LICENSE
